offvsix/__init__.py
offvsix/main.py
offvsix-0.1.5.dist-info/LICENSE
offvsix-0.1.5.dist-info/METADATA
offvsix-0.1.5.dist-info/WHEEL
offvsix-0.1.5.dist-info/entry_points.txt
offvsix-0.1.5.dist-info/RECORD
